[
  {
    "name": "Tia Brazda - Smile",
    "count": 4
  },
  {
    "name": "Peggy Lee - Riders In The Sky",
    "count": 4
  },
  {
    "name": "Chrissie Hynde & The Valve Bone Woe Ensemble - Hello, Young Lovers",
    "count": 4
  },
  {
    "name": "Kameron Mantell - Will You Still Love Me Tomorrow",
    "count": 4
  },
  {
    "name": "Martin Cilia - Strawberry Fields Forever",
    "count": 3
  },
  {
    "name": "The Beatles - Day in the Life",
    "count": 3
  },
  {
    "name": "The Desolate Coast - Tangled Up In Macramé",
    "count": 3
  },
  {
    "name": "Molly Tuttle & Golden Highway - Here in California (feat. AJ Lee and Jack Tuttle)",
    "count": 3
  },
  {
    "name": "Amphibian Man - Philosopher's Stone",
    "count": 3
  },
  {
    "name": "The Byrds - Lay Down Your Weary Tune",
    "count": 3
  },
  {
    "name": "The Rolling Stones - Dead Flowers",
    "count": 3
  },
  {
    "name": "Lee Moses - Diana (From N.Y.C.)",
    "count": 3
  },
  {
    "name": "Nick Curran & The Lowlifes - Reform School Girl",
    "count": 3
  },
  {
    "name": "RvB - Actor in the Dream of God",
    "count": 3
  },
  {
    "name": "Talking Heads - Road to Nowhere",
    "count": 3
  },
  {
    "name": "King Dude - Seven Beers With The Wrong Woman",
    "count": 3
  },
  {
    "name": "Chris Rea - On The Beach",
    "count": 3
  },
  {
    "name": "Jay Poisön and the Bat People - Slumber of the Bat People",
    "count": 3
  },
  {
    "name": "Sam Cooke - Good Times",
    "count": 3
  },
  {
    "name": "Morphine - You Look Like Rain",
    "count": 3
  },
  {
    "name": "Manic Vila - Justa Couple a Birds",
    "count": 3
  },
  {
    "name": "Tiger Shark Nilsson - Clickbait",
    "count": 3
  },
  {
    "name": "Los Fuckin´ Surfer Smokers, The Atlantics - Reef Break",
    "count": 3
  },
  {
    "name": "The Mermers - Surf Wax Transylvania",
    "count": 3
  },
  {
    "name": "Blondie - Denis",
    "count": 3
  },
  {
    "name": "Austin Leonard Jones - Rodeo in Galilee",
    "count": 3
  },
  {
    "name": "RPS Surfers - East St Louis Toodle-Oo",
    "count": 3
  },
  {
    "name": "Tom Waits - Anywhere I Lay My Head",
    "count": 3
  },
  {
    "name": "Richie Havens - Drown In My Own Tears",
    "count": 3
  },
  {
    "name": "Johnny Cash - Personal Jesus",
    "count": 3
  }
]