[
  {
    "name": "Iggy And The Stooges - Louie Louie (Live)",
    "count": 1
  },
  {
    "name": "The New York Dolls - Babylon",
    "count": 1
  },
  {
    "name": "Los Twangers - La Casa Del Sol Naciente",
    "count": 1
  },
  {
    "name": "Thalia Zedek Band - Tolls",
    "count": 1
  },
  {
    "name": "Number Nine - Jepardy",
    "count": 1
  },
  {
    "name": "Stereophonic Space Sound Unlimited - Chicken Skin",
    "count": 1
  },
  {
    "name": "The Atlantics - Surfin' Sunrise",
    "count": 1
  },
  {
    "name": "Cheap Violent Cats - The Model:",
    "count": 1
  },
  {
    "name": "P Paul Fenech - The Return to Guts Crossing",
    "count": 1
  },
  {
    "name": "Sant Anna Bay Coconuts - Fiber Shaping",
    "count": 1
  },
  {
    "name": "The ChuGuysters - Escape In The Fifth Gear",
    "count": 1
  },
  {
    "name": "Odicolon - Fever",
    "count": 1
  },
  {
    "name": "Humanga Danga - Luau Cake",
    "count": 1
  },
  {
    "name": "Doyley And The Twanglords - Surf Bitch",
    "count": 1
  },
  {
    "name": "The Tourmaliners - Tourmaliner Twist",
    "count": 1
  },
  {
    "name": "Jason Janik - AM Waves",
    "count": 1
  },
  {
    "name": "Los Dangers - González",
    "count": 1
  },
  {
    "name": "THE METABOLITES - Climate of Catastrophe",
    "count": 1
  },
  {
    "name": "The Surf Raiders - Tsunami",
    "count": 1
  },
  {
    "name": "The Screaming Seagulls - Hypnic Jerk",
    "count": 1
  },
  {
    "name": "Link Wray & His Ray Men - Alone",
    "count": 1
  },
  {
    "name": "The Sentinals - Twilighter",
    "count": 1
  },
  {
    "name": "Guitar UP - Surfboard",
    "count": 1
  },
  {
    "name": "Amphibian Man - Pattern",
    "count": 1
  },
  {
    "name": "Nick Willett - Do You Love Me",
    "count": 1
  },
  {
    "name": "Ken Pomeroy - Stranger",
    "count": 1
  },
  {
    "name": "The Turks - Baja",
    "count": 1
  },
  {
    "name": "Boss Caine - Champagne (Loved By Trouble, Troubled By Love)",
    "count": 1
  },
  {
    "name": "Los Coronas - Rockaway Surfers",
    "count": 1
  },
  {
    "name": "Matthews Southern Comfort - If I Were a Carpenter",
    "count": 1
  }
]